{
  "player_metadata": {
    "columns": [
      {
        "column_name": "id",
        "column_type": "integer",
        "primary_key": true,
        "not_null": true
      },
      {
        "column_name": "first_name",
        "column_type": "text"
      },
      {
        "column_name": "second_name",
        "column_type": "text"
      }
    ]
  },
  "player_season_totals": {
    "columns": [
      {
        "column_name": "id",
        "column_type": "integer",
        "primary_key": true,
        "not_null": true
      },
      {
        "column_name": "goals_scored",
        "column_type": "integer"
      },
      {
        "column_name": "assists",
        "column_type": "integer"
      },
      {
        "column_name": "total_points",
        "column_type": "integer"
      },
      {
        "column_name": "minutes",
        "column_type": "integer"
      },
      {
        "column_name": "goals_conceded",
        "column_type": "integer"
      },
      {
        "column_name": "creativity",
        "column_type": "double precision"
      },
      {
        "column_name": "influence",
        "column_type": "double precision"
      },
      {
        "column_name": "threat",
        "column_type": "double precision"
      },
      {
        "column_name": "bonus",
        "column_type": "integer"
      },
      {
        "column_name": "bps",
        "column_type": "integer"
      },
      {
        "column_name": "ict_index",
        "column_type": "double precision"
      },
      {
        "column_name": "clean_sheets",
        "column_type": "integer"
      },
      {
        "column_name": "red_cards",
        "column_type": "integer"
      },
      {
        "column_name": "yellow_cards",
        "column_type": "integer"
      },
      {
        "column_name": "selected_by_percent",
        "column_type": "double precision"
      },
      {
        "column_name": "now_cost",
        "column_type": "integer"
      },
      {
        "column_name": "element_type",
        "column_type": "text"
      }
    ]
  },
  "player_gameweek_data": {
    "columns": [
      {
        "column_name": "id",
        "column_type": "integer",
        "primary_key": true,
        "not_null": true
      },
      {
        "column_name": "element",
        "column_type": "integer"
      },
      {
        "column_name": "position",
        "column_type": "text"
      },
      {
        "column_name": "xp",
        "column_type": "double precision"
      },
      {
        "column_name": "assists",
        "column_type": "integer"
      },
      {
        "column_name": "bonus",
        "column_type": "integer"
      },
      {
        "column_name": "bps",
        "column_type": "integer"
      },
      {
        "column_name": "clean_sheets",
        "column_type": "integer"
      },
      {
        "column_name": "fixture",
        "column_type": "integer"
      },
      {
        "column_name": "goals_conceded",
        "column_type": "integer"
      },
      {
        "column_name": "goals_scored",
        "column_type": "integer"
      },
      {
        "column_name": "ict_index",
        "column_type": "double precision"
      },
      {
        "column_name": "influence",
        "column_type": "double precision"
      },
      {
        "column_name": "creativity",
        "column_type": "double precision"
      },
      {
        "column_name": "threat",
        "column_type": "double precision"
      },
      {
        "column_name": "kickoff_time",
        "column_type": "text"
      },
      {
        "column_name": "minutes",
        "column_type": "integer"
      },
      {
        "column_name": "opponent_team",
        "column_type": "integer"
      },
      {
        "column_name": "own_goals",
        "column_type": "integer"
      },
      {
        "column_name": "penalties_missed",
        "column_type": "integer"
      },
      {
        "column_name": "saves",
        "column_type": "integer"
      },
      {
        "column_name": "penalties_saved",
        "column_type": "integer"
      },
      {
        "column_name": "yellow_cards",
        "column_type": "integer"
      },
      {
        "column_name": "red_cards",
        "column_type": "integer"
      },
      {
        "column_name": "round",
        "column_type": "integer"
      },
      {
        "column_name": "selected",
        "column_type": "integer"
      },
      {
        "column_name": "team_a_score",
        "column_type": "text"
      },
      {
        "column_name": "team_h_score",
        "column_type": "text"
      },
      {
        "column_name": "total_points",
        "column_type": "integer"
      },
      {
        "column_name": "value",
        "column_type": "integer"
      },
      {
        "column_name": "was_home",
        "column_type": "boolean"
      }
    ]
  },
  "team_metadata": {
    "columns": [
      {
        "column_name": "id",
        "column_type": "integer",
        "primary_key": true,
        "not_null": true
      },
      {
        "column_name": "code",
        "column_type": "integer"
      },
      {
        "column_name": "name",
        "column_type": "text"
      },
      {
        "column_name": "short_name",
        "column_type": "text"
      }
    ]
  },
  "team_understat_data": {
    "columns": [
      {
        "column_name": "id",
        "column_type": "text",
        "primary_key": true,
        "not_null": true
      },
      {
        "column_name": "team_id",
        "column_type": "integer"
      },
      {
        "column_name": "gameweek",
        "column_type": "integer"
      },
      {
        "column_name": "h_a",
        "column_type": "text"
      },
      {
        "column_name": "xg",
        "column_type": "double precision"
      },
      {
        "column_name": "npxg",
        "column_type": "double precision"
      },
      {
        "column_name": "xga",
        "column_type": "double precision"
      },
      {
        "column_name": "npxga",
        "column_type": "double precision"
      },
      {
        "column_name": "ppda",
        "column_type": "text"
      },
      {
        "column_name": "ppda_allowed",
        "column_type": "text"
      },
      {
        "column_name": "deep",
        "column_type": "integer"
      },
      {
        "column_name": "deep_allowed",
        "column_type": "integer"
      },
      {
        "column_name": "scored",
        "column_type": "integer"
      },
      {
        "column_name": "missed",
        "column_type": "integer"
      },
      {
        "column_name": "xpts",
        "column_type": "double precision"
      },
      {
        "column_name": "result",
        "column_type": "text"
      },
      {
        "column_name": "date",
        "column_type": "date"
      },
      {
        "column_name": "pts",
        "column_type": "integer"
      },
      {
        "column_name": "npxgd",
        "column_type": "double precision"
      }
    ]
  }
}
